QuiltiX/__init__.py
QuiltiX/__main__.py
QuiltiX/constants.py
QuiltiX/mx_node.py
QuiltiX/quiltix.py
QuiltiX/qx_node.py
QuiltiX/qx_node_property.py
QuiltiX/qx_node_property_widgets.py
QuiltiX/qx_nodegraph.py
QuiltiX/qx_nodegraph_tabsearch.py
QuiltiX/qx_nodegraph_viewer.py
QuiltiX/qx_plugin.py
QuiltiX/qx_port.py
QuiltiX/qx_subnodegraph.py
QuiltiX/style.qss
QuiltiX/usd_render_settings.py
QuiltiX/usd_stage.py
QuiltiX/usd_stage_tree.py
QuiltiX/usd_stage_view.py
QuiltiX/hotkeys/__init__.py
QuiltiX/hotkeys/hotkey_functions.py
QuiltiX/hotkeys/hotkeys.json
QuiltiX/resources/geometry/matx_shaderball_uv.usdc
QuiltiX/resources/hdris/boiler_room_1k.exr
QuiltiX/resources/hdris/cayley_interior_1k.exr
QuiltiX/resources/hdris/dreifaltigkeitsberg_1k.hdr
QuiltiX/resources/icons/check-icon.png
QuiltiX/resources/icons/close-icon.png
QuiltiX/resources/icons/drop-down-arrow-closed-icon.png
QuiltiX/resources/icons/drop-down-arrow-icon.png
QuiltiX/resources/icons/eye_invisible.svg
QuiltiX/resources/icons/eye_visible.svg
QuiltiX/resources/icons/help.png
QuiltiX/resources/icons/quiltix-logo-x.png
QuiltiX/resources/icons/update.svg
QuiltiX/resources/icons/window-restore-icon.png
QuiltiX/resources/materials/open_pbr_surface.mtlx
QuiltiX/resources/materials/standard_surface.mtlx
QuiltiX/resources/materials/Black_Upholstery_1k_8b/Black_Upholstery.mtlx
QuiltiX/resources/materials/Black_Upholstery_1k_8b/textures/Black_Upholstery_height.png
QuiltiX/resources/materials/Black_Upholstery_1k_8b/textures/Black_Upholstery_normal.png
QuiltiX/resources/materials/Black_Upholstery_1k_8b/textures/Black_Upholstery_roughness.png
QuiltiX/resources/materials/Copper_Old_1k_8b/Copper_Old.mtlx
QuiltiX/resources/materials/Copper_Old_1k_8b/textures/Copper_Old_baseColor.png
QuiltiX/resources/materials/Copper_Old_1k_8b/textures/Copper_Old_bump.png
QuiltiX/resources/materials/Copper_Old_1k_8b/textures/Copper_Old_diffuse.png
QuiltiX/resources/materials/Copper_Old_1k_8b/textures/Copper_Old_normal.png
quiltix-0.8.0.dist-info/licenses/LICENSE
quiltix-0.8.0.dist-info/licenses/NOTICE
quiltix-0.8.0.dist-info/METADATA
quiltix-0.8.0.dist-info/WHEEL
quiltix-0.8.0.dist-info/entry_points.txt
quiltix-0.8.0.dist-info/top_level.txt
quiltix-0.8.0.dist-info/RECORD
