Metadata-Version: 2.4
Name: QuiltiX
Version: 0.8.0
Summary: MaterialX Graphical Node Editor
Author-email: Manuel Köster <manuelkoestercg@gmail.com>, Richard Frangenberg <richard@prism-pipeline.com>
License:                                  Apache License
Project-URL: Homepage, https://github.com/PrismPipeline/QuiltiX
Project-URL: Bug Reports, https://github.com/PrismPipeline/QuiltiX/issues
Project-URL: Source, https://github.com/PrismPipeline/QuiltiX
Keywords: openusd,materialx
Classifier: Programming Language :: Python :: 3
Classifier: License :: OSI Approved :: Apache Software License
Classifier: Operating System :: POSIX :: Linux
Classifier: Operating System :: MacOS :: MacOS X
Classifier: Operating System :: Microsoft :: Windows :: Windows 10
Classifier: Topic :: Multimedia :: Graphics :: Editors
Requires-Python: ~=3.11
License-File: LICENSE
License-File: NOTICE
Requires-Dist: pluggy
Requires-Dist: materialx~=1.39
Requires-Dist: QtPy
Requires-Dist: PySide6~=6.5.0
Requires-Dist: PyOpenGL
Requires-Dist: PyOpenGL_accelerate
Requires-Dist: NodeGraphQt-QuiltiX-fork~=0.7
Provides-Extra: dev
Requires-Dist: black; extra == "dev"
Requires-Dist: ruff; extra == "dev"
Requires-Dist: pytest; extra == "dev"
Requires-Dist: pytest-qt; extra == "dev"
Requires-Dist: pytest-cov; extra == "dev"
Provides-Extra: plugins
Requires-Dist: pygments; extra == "plugins"
Requires-Dist: materialxjson; extra == "plugins"
Provides-Extra: all
Requires-Dist: QuiltiX[dev]; extra == "all"
Requires-Dist: QuiltiX[plugins]; extra == "all"
Dynamic: license-file
